lavender_data/__init__.py
lavender_data/__main__.py
lavender_data/client/__init__.py
lavender_data/client/__main__.py
lavender_data/client/api.py
lavender_data/client/cli/__init__.py
lavender_data/client/cli/api_call.py
lavender_data/client/converters/__init__.py
lavender_data/client/converters/abc.py
lavender_data/client/converters/plain.py
lavender_data/client/converters/webdataset.py
lavender_data/client/iteration.py
lavender_data/logging.py
lavender_data/serialize.py
lavender_data/server/__init__.py
lavender_data/server/__main__.py
lavender_data/server/app.py
lavender_data/server/auth/__init__.py
lavender_data/server/auth/api_key_auth.py
lavender_data/server/auth/cluster_auth.py
lavender_data/server/auth/header.py
lavender_data/server/background_worker/__init__.py
lavender_data/server/background_worker/background_worker.py
lavender_data/server/background_worker/memory.py
lavender_data/server/background_worker/process_pool.py
lavender_data/server/cache/__init__.py
lavender_data/server/cache/abc.py
lavender_data/server/cache/inmemory.py
lavender_data/server/cache/redis.py
lavender_data/server/cli/__init__.py
lavender_data/server/cli/create_api_key.py
lavender_data/server/cli/daemon.py
lavender_data/server/cli/db.py
lavender_data/server/cli/run.py
lavender_data/server/dataset/__init__.py
lavender_data/server/dataset/preview.py
lavender_data/server/dataset/statistics.py
lavender_data/server/db/__init__.py
lavender_data/server/db/alembic.ini
lavender_data/server/db/migrations/README
lavender_data/server/db/migrations/env.py
lavender_data/server/db/migrations/script.py.mako
lavender_data/server/db/migrations/versions/10a13fa2ef30_init.py
lavender_data/server/db/migrations/versions/12be9c758381_add_categorizer.py
lavender_data/server/db/migrations/versions/402ed556c2da_.py
lavender_data/server/db/migrations/versions/b79c963ecb4d_.py
lavender_data/server/db/migrations/versions/bcbf85d70ecf_.py
lavender_data/server/db/migrations/versions/cd76eadd663a_.py
lavender_data-0.1.10.dist-info/LICENSE
lavender_data-0.1.10.dist-info/METADATA
lavender_data-0.1.10.dist-info/WHEEL
lavender_data-0.1.10.dist-info/entry_points.txt
lavender_data-0.1.10.dist-info/RECORD
