Metadata-Version: 2.1
Name: lavender-data
Version: 0.1.10
Summary: Load & evolve datasets efficiently
Home-page: https://github.com/fal-ai/lavender-data
License: Apache-2.0
Author: Hanch Han
Author-email: cndghks15@gmail.com
Requires-Python: >=3.10,<3.14
Classifier: License :: OSI Approved :: Apache Software License
Classifier: Programming Language :: Python :: 3
Classifier: Programming Language :: Python :: 3.10
Classifier: Programming Language :: Python :: 3.11
Classifier: Programming Language :: Python :: 3.12
Classifier: Programming Language :: Python :: 3.13
Provides-Extra: hf
Provides-Extra: pgsql
Provides-Extra: redis
Provides-Extra: s3
Provides-Extra: wds
Requires-Dist: alembic (>=1.15.2,<2.0.0)
Requires-Dist: attrs (>=22.2.0)
Requires-Dist: boto3 (>=1.38.13,<2.0.0) ; extra == "s3"
Requires-Dist: fastapi[standard] (==0.115.6)
Requires-Dist: filetype (>=1.2.0,<2.0.0)
Requires-Dist: httpx (>=0.20.0,<0.29.0)
Requires-Dist: huggingface-hub (>=0.31.1,<0.32.0) ; extra == "hf"
Requires-Dist: numpy (==2.1.2)
Requires-Dist: psycopg2-binary (>=2.9.10,<3.0.0) ; extra == "pgsql"
Requires-Dist: pyarrow (==19.0.1)
Requires-Dist: pydantic-settings (>=2.8.1,<3.0.0)
Requires-Dist: python-daemon (>=3.1.2,<4.0.0)
Requires-Dist: python-dateutil (>=2.8.0,<3.0.0)
Requires-Dist: redis[hiredis] (>=5.2.1,<6.0.0) ; extra == "redis"
Requires-Dist: sqlmodel (>=0.0.23,<0.0.24)
Requires-Dist: ujson (>=5.10.0,<6.0.0)
Requires-Dist: webdataset (>=0.2.111,<0.3.0) ; extra == "wds"
Project-URL: Changelog, https://docs.lavenderdata.com/release-notes
Project-URL: Documentation, https://docs.lavenderdata.com
Project-URL: Repository, https://github.com/fal-ai/lavender-data
